SECUREVOTE/S1-T7.v
module comparator(input [3:0]A,input [3:0]B,output e);
wire [3:0]x;
assign x[0]=~(A[0]^B[0]);
assign x[1]=~(A[1]^B[1]);
assign x[2]=~(A[2]^B[2]);
assign x[3]=~(A[3]^B[3]);
assign e=x[0]&x[1]&x[2]&x[3];
endmodule
 
module password(input [3:0]A1,input [3:0]A2,input [3:0]A3,input [3:0]A4,input [3:0]B1,input [3:0]B2,input [3:0]B3,input [3:0]B4,output o);
wire e1,e2,e3,e4;
comparator C1(A1,B1,e1);
comparator C2(A2,B2,e2);
comparator C3(A3,B3,e3);
comparator C4(A4,B4,e4);
assign o= e1 & e2 & e3 & e4;
endmodule

module voting_machine (
    input [3:0]A1,input [3:0]A2,input [3:0]A3,input [3:0]A4,input [3:0]B1,input [3:0]B2,input [3:0]B3,input [3:0]B4,output o,
    input wire clk1,
    input wire clk2,
    input wire clk3,
    input wire clk4,
    input wire [3:0]count1,
    input wire [3:0]count2,
    input wire [3:0]count3,
    input wire [3:0]count4,
    output reg [3:0] counter1,
    output reg [3:0] counter2,
    output reg [3:0] counter3,
    output reg [3:0] counter4,
    input wire display,
    output reg P,
    output reg Q,
    output reg R,
    output reg S
);
password p1(A1,A2,A3,A4,B1,B2,B3,B4,o);
always@(clk1==0 & clk2==0 & clk3==0 & clk4==0 &o==1'b1 & display==0)
begin
    counter1 <= 4'b0000;
    counter2 <= 4'b0000;
    counter3 <= 4'b0000;
    counter4 <= 4'b0000;
end
always@(clk1==0 & clk2==0 & clk3==0 & clk4==0 &o==1'b0 & display==0)
begin
    counter1 <= 4'b0000;
    counter2 <= 4'b0000;
    counter3 <= 4'b0000;
    counter4 <= 4'b0000;
end
always @(posedge clk1 & clk2==0 &clk3==0 &clk4==0 &o==1'b0 & display==0 ) begin
    counter1 <= count1;
    counter2 <= count2;
    counter3 <= count3;
    counter4 <= count4;
end
always @(posedge clk2 & clk1==0 &clk3==0 &clk4==0 &o==1'b0 & display==0) begin
    counter2 <= count2;
    counter1 <= count1;
    counter3 <= count3;
    counter4 <= count4;
end
always @(posedge clk3 &clk2==0 &clk1==0 &clk4==0 &o==1'b0 & display==0) begin
    counter3 <= count3;
    counter1 <= count1;
    counter4 <= count4;
    counter2 <= count2;
end
always @(posedge clk4 & clk1==0 &clk3==0 &clk2==0 &o==1'b0 & display==0) begin
    counter4 <= count4;
     counter1 <= count1;
     counter2 <= count2;
     counter3 <= count3;
end
always @(posedge clk1 & clk2==0 &clk3==0 &clk4==0 &o==1'b1 & display==0 ) begin
    counter1 <= count1 + 4'b0001;
    counter2 <= count2;
    counter3 <= count3;
    counter4 <= count4;
end
always @(posedge clk2 & clk1==0 &clk3==0 &clk4==0 &o==1'b1 & display==0) begin
    counter2 <= count2 + 4'b0001;
    counter1 <= count1;
    counter3 <= count3;
    counter4 <= count4;
end
always @(posedge clk3 &clk2==0 &clk1==0 &clk4==0 &o==1'b1 & display==0) begin
    counter3 <= count3 + 4'b0001;
    counter1 <= count1;
    counter4 <= count4;
    counter2 <= count2;
end
always @(posedge clk4 & clk1==0 &clk3==0 &clk2==0 &o==1'b1 & display==0) begin
    counter4 <= count4 + 4'b0001;
     counter1 <= count1;
     counter2 <= count2;
     counter3 <= count3;
end
always @(display==1'b1) begin
     if (counter1 >= counter2 && counter1 >= counter3 && counter1 >= counter4)
                P <= 1'b1;
            else
                P <= 1'b0;

            if (counter2 >= counter1 && counter2 >= counter3 && counter2 >= counter4)
                Q <= 1'b1;
            else
                Q <= 1'b0;

            if (counter3 >= counter1 && counter3 >= counter2 && counter3 >= counter4)
                R <= 1'b1;
            else
                R <= 1'b0;

            if (counter4 >= counter1 && counter4 >= counter2 && counter4 >= counter3)
                S <= 1'b1;
            else
                S <= 1'b0;
end
endmodule

SECUREVOTE/S1-T7_tb.v
module voting_machine_tb;
reg clk1, clk2, clk3, clk4,display;
reg [3:0] count1,A1,A2,A3,A4,B1,B2,B3,B4;
reg [3:0] count2;
reg [3:0] count3;
reg [3:0] count4;
wire o,P,Q,R,S;
wire [3:0] counter1;
wire [3:0] counter2;
wire [3:0] counter3;
wire [3:0] counter4;
// Instantiate the voting_machine module
voting_machine uut (.A1(A1),.A2(A2),.A3(A3),.A4(A4),.B1(B1),.B2(B2),.B3(B3),.B4(B4),.o(o),
    .clk1(clk1),
    .clk2(clk2),
    .clk3(clk3),
    .clk4(clk4),
    .count1(count1),
    .count2(count2),
    .count3(count3),
    .count4(count4),
    .counter1(counter1),
    .counter2(counter2),
    .counter3(counter3),
    .counter4(counter4),
    .display(display),
    .P(P),
    .Q(Q),
    .R(R),
    .S(S)
);

initial begin
    $dumpfile("wave.vcd");
    $dumpvars(0, voting_machine_tb);
    clk1 = 1'b0;
    clk2 = 1'b0;
    clk3 = 1'b0;
    clk4 = 1'b0;
    display=1'b0;
    A1=4'd2;A2=4'd9;A3=4'd8;A4=4'd7;B1=4'd2;B2=4'd9;B3=4'd8;B4=4'd7;
    count1<=4'b0000;
    count2<=4'b0000;
    count3<=4'b0000;
    count4<=4'b0000;
    $display("-----------------------------------------------------------------------------------------------------------------------------------------------------");
    $display("| INPUT PASSWORD | VALID PASSWORD | ELIGIBILITY | BUTTON-A |   COUNT-A   | BUTTON-B |   COUNT-B   | BUTTON-C |   COUNT-C   | BUTTON-D |   COUNT-D   |");
    $display("|        A       |        B       |   match(o)  |    clk1  |   counter1  |   clk2   |   counter2  |   clk3   |   counter3  |   clk4   |   counter4  |");
    $display("-----------------------------------------------------------------------------------------------------------------------------------------------------");
    //$monitor("%d\t%d\t%d\t%d\t%d\t%d\t%d\t%d\t%d", $time, counter1,counter2, clk2,counter3, clk3,counter4, clk4);
    repeat (2) begin
        $monitor("|  %d %d %d %d   |  %d %d %d %d   |       %b     |    %d     |      %d     |     %d    |     %d      |    %d     |     %d      |     %d    |     %d      |",A1,A2,A3,A4,B1,B2,B3,B4,o, clk1,counter1,clk2,counter2, clk3, counter3, clk4,counter4);
        #10 A1=4'd2;A2=4'd9;A3=4'd8;A4=4'd7;B1=4'd2;B2=4'd9;B3=4'd8;B4=4'd7;clk1=1'b1; clk2=1'b0; clk3=1'b0; clk4=1'b0;
        #10 count1<=counter1;
        #10 count2<=counter2;
        #10 count3<=counter3;
        #10 count4<=counter4;
        #10 A1=4'd8;A2=4'd4;A3=4'd2;A4=4'd1;B1=4'd8;B2=4'd2;B3=4'd4;B4=4'd0;clk1=1'b0; clk2=1'b0; clk3=1'b1; clk4=1'b0;
        #10 count1<=counter1;
        #10 count2<=counter2;
        #10 count3<=counter3;
        #10 count4<=counter4; 
        #10 A1=4'd2;A2=4'd3;A3=4'd4;A4=4'd5;B1=4'd2;B2=4'd3;B3=4'd4;B4=4'd5;clk1=1'b0; clk2=1'b0; clk3=1'b0; clk4=1'b1;
        #10 count1<=counter1;
        #10 count2<=counter2;
        #10 count3<=counter3;
        #10 count4<=counter4; 
        #10 A1=4'd2;A2=4'd9;A3=4'd8;A4=4'd7;B1=4'd2;B2=4'd9;B3=4'd8;B4=4'd7;clk1=1'b0; clk2=1'b0; clk3=1'b1; clk4=1'b0;  
        #10 count1<=counter1;
        #10 count2<=counter2;
        #10 count3<=counter3;
        #10 count4<=counter4; 
        #10 A1=4'd3;A2=4'd2;A3=4'd1;A4=4'd7;B1=4'd2;B2=4'd9;B3=4'd8;B4=4'd7;clk1=1'b0; clk2=1'b1; clk3=1'b0; clk4=1'b0;
        #10 count1<=counter1;
        #10 count2<=counter2;
        #10 count3<=counter3;
        #10 count4<=counter4;
        #10 A1=4'd2;A2=4'd9;A3=4'd8;A4=4'd7;B1=4'd3;B2=4'd5;B3=4'd9;B4=4'd7;clk1=1'b1; clk2=1'b0; clk3=1'b0; clk4=1'b0;
        #10 count1<=counter1;
        #10 count2<=counter2;
        #10 count3<=counter3;
        #10 count4<=counter4;
        #10 A1=4'd8;A2=4'd4;A3=4'd2;A4=4'd1;B1=4'd8;B2=4'd4;B3=4'd2;B4=4'd1;clk1=1'b0; clk2=1'b0; clk3=1'b1; clk4=1'b0;
        #10 count1<=counter1;
        #10 count2<=counter2;
        #10 count3<=counter3;
        #10 count4<=counter4; 
        #10 A1=4'd2;A2=4'd3;A3=4'd4;A4=4'd5;B1=4'd8;B2=4'd7;B3=4'd4;B4=4'd5;clk1=1'b0; clk2=1'b0; clk3=1'b0; clk4=1'b1;
        #10 count1<=counter1;
        #10 count2<=counter2;
        #10 count3<=counter3;
        #10 count4<=counter4; 
        #10 A1=4'd2;A2=4'd9;A3=4'd8;A4=4'd7;B1=4'd3;B2=4'd6;B3=4'd8;B4=4'd7;clk1=1'b0; clk2=1'b0; clk3=1'b1; clk4=1'b0;  
        #10 count1<=counter1;
        #10 count2<=counter2;
        #10 count3<=counter3;
        #10 count4<=counter4; 
        #10 A1=4'd1;A2=4'd1;A3=4'd2;A4=4'd2;B1=4'd1;B2=4'd1;B3=4'd2;B4=4'd2;clk1=1'b0; clk2=1'b1; clk3=1'b0; clk4=1'b0;
        #10 count1<=counter1;
        #10 count2<=counter2;
        #10 count3<=counter3;
        #10 count4<=counter4;      
    end
    #1000;
    display=1'b1;
    $display("-----------------------------------------------------------------------------------------------------------------------------------------------------");
    $display("WINNER:");
    $display("A   B    C    D");
    $monitor("%b   %b    %b    %b",P,Q,R,S);
    #10 $display("-----------------------------------------------------------------------------------------------------------------------------------------------------");
end
endmodule

Verilog/S1-T7.vcd
$date
	Thu Nov  2 21:35:20 2023
$end
$version
	Icarus Verilog
$end
$timescale
	1s
$end
$scope module voting_machine_tb $end
$var wire 1 ! o $end
$var wire 4 " counter4 [3:0] $end
$var wire 4 # counter3 [3:0] $end
$var wire 4 $ counter2 [3:0] $end
$var wire 4 % counter1 [3:0] $end
$var wire 1 & S $end
$var wire 1 ' R $end
$var wire 1 ( Q $end
$var wire 1 ) P $end
$var reg 4 * A1 [3:0] $end
$var reg 4 + A2 [3:0] $end
$var reg 4 , A3 [3:0] $end
$var reg 4 - A4 [3:0] $end
$var reg 4 . B1 [3:0] $end
$var reg 4 / B2 [3:0] $end
$var reg 4 0 B3 [3:0] $end
$var reg 4 1 B4 [3:0] $end
$var reg 1 2 clk1 $end
$var reg 1 3 clk2 $end
$var reg 1 4 clk3 $end
$var reg 1 5 clk4 $end
$var reg 4 6 count1 [3:0] $end
$var reg 4 7 count2 [3:0] $end
$var reg 4 8 count3 [3:0] $end
$var reg 4 9 count4 [3:0] $end
$var reg 1 : display $end
$scope module uut $end
$var wire 4 ; A1 [3:0] $end
$var wire 4 < A2 [3:0] $end
$var wire 4 = A3 [3:0] $end
$var wire 4 > A4 [3:0] $end
$var wire 4 ? B1 [3:0] $end
$var wire 4 @ B2 [3:0] $end
$var wire 4 A B3 [3:0] $end
$var wire 4 B B4 [3:0] $end
$var wire 1 2 clk1 $end
$var wire 1 3 clk2 $end
$var wire 1 4 clk3 $end
$var wire 1 5 clk4 $end
$var wire 4 C count1 [3:0] $end
$var wire 4 D count2 [3:0] $end
$var wire 4 E count3 [3:0] $end
$var wire 4 F count4 [3:0] $end
$var wire 1 : display $end
$var wire 1 ! o $end
$var reg 1 ) P $end
$var reg 1 ( Q $end
$var reg 1 ' R $end
$var reg 1 & S $end
$var reg 4 G counter1 [3:0] $end
$var reg 4 H counter2 [3:0] $end
$var reg 4 I counter3 [3:0] $end
$var reg 4 J counter4 [3:0] $end
$scope module p1 $end
$var wire 4 K A1 [3:0] $end
$var wire 4 L A2 [3:0] $end
$var wire 4 M A3 [3:0] $end
$var wire 4 N A4 [3:0] $end
$var wire 4 O B1 [3:0] $end
$var wire 4 P B2 [3:0] $end
$var wire 4 Q B3 [3:0] $end
$var wire 4 R B4 [3:0] $end
$var wire 1 ! o $end
$var wire 1 S e4 $end
$var wire 1 T e3 $end
$var wire 1 U e2 $end
$var wire 1 V e1 $end
$scope module C1 $end
$var wire 4 W A [3:0] $end
$var wire 4 X B [3:0] $end
$var wire 1 V e $end
$var wire 4 Y x [3:0] $end
$upscope $end
$scope module C2 $end
$var wire 4 Z A [3:0] $end
$var wire 4 [ B [3:0] $end
$var wire 1 U e $end
$var wire 4 \ x [3:0] $end
$upscope $end
$scope module C3 $end
$var wire 4 ] A [3:0] $end
$var wire 4 ^ B [3:0] $end
$var wire 1 T e $end
$var wire 4 _ x [3:0] $end
$upscope $end
$scope module C4 $end
$var wire 4 ` A [3:0] $end
$var wire 4 a B [3:0] $end
$var wire 1 S e $end
$var wire 4 b x [3:0] $end
$upscope $end
$upscope $end
$upscope $end
$upscope $end
$enddefinitions $end
#0
$dumpvars
b1111 b
b111 a
b111 `
b1111 _
b1000 ^
b1000 ]
b1111 \
b1001 [
b1001 Z
b1111 Y
b10 X
b10 W
1V
1U
1T
1S
b111 R
b1000 Q
b1001 P
b10 O
b111 N
b1000 M
b1001 L
b10 K
b0 J
b0 I
b0 H
b0 G
b0 F
b0 E
b0 D
b0 C
b111 B
b1000 A
b1001 @
b10 ?
b111 >
b1000 =
b1001 <
b10 ;
0:
b0 9
b0 8
b0 7
b0 6
05
04
03
02
b111 1
b1000 0
b1001 /
b10 .
b111 -
b1000 ,
b1001 +
b10 *
0)
0(
0'
0&
b0 %
b0 $
b0 #
b0 "
1!
$end
#10
b1 %
b1 G
12
#20
b1 6
b1 C
#60
b0 #
b0 I
0!
0S
0T
0U
b1110 b
b1001 _
b1001 \
14
02
b0 1
b0 B
b0 R
b0 a
b100 0
b100 A
b100 Q
b100 ^
b10 /
b10 @
b10 P
b10 [
b1000 .
b1000 ?
b1000 O
b1000 X
b1 -
b1 >
b1 N
b1 `
b10 ,
b10 =
b10 M
b10 ]
b100 +
b100 <
b100 L
b100 Z
b1000 *
b1000 ;
b1000 K
b1000 W
#110
b1 "
b1 J
1!
1S
1T
1U
b1111 b
b1111 _
b1111 \
15
04
b101 1
b101 B
b101 R
b101 a
b11 /
b11 @
b11 P
b11 [
b10 .
b10 ?
b10 O
b10 X
b101 -
b101 >
b101 N
b101 `
b100 ,
b100 =
b100 M
b100 ]
b11 +
b11 <
b11 L
b11 Z
b10 *
b10 ;
b10 K
b10 W
#150
b1 9
b1 F
#160
b1 #
b1 I
05
14
b111 1
b111 B
b111 R
b111 a
b1000 0
b1000 A
b1000 Q
b1000 ^
b1001 /
b1001 @
b1001 P
b1001 [
b111 -
b111 >
b111 N
b111 `
b1000 ,
b1000 =
b1000 M
b1000 ]
b1001 +
b1001 <
b1001 L
b1001 Z
#190
b1 8
b1 E
#210
b0 $
b0 H
0!
0V
0T
0U
b110 _
b100 \
b1110 Y
04
13
b1 ,
b1 =
b1 M
b1 ]
b10 +
b10 <
b10 L
b10 Z
b11 *
b11 ;
b11 K
b11 W
#260
b1110 _
b11 \
03
12
b1001 0
b1001 A
b1001 Q
b1001 ^
b101 /
b101 @
b101 P
b101 [
b11 .
b11 ?
b11 O
b11 X
b1000 ,
b1000 =
b1000 M
b1000 ]
b1001 +
b1001 <
b1001 L
b1001 Z
b10 *
b10 ;
b10 K
b10 W
#310
b10 #
b10 I
1!
1T
1V
1U
b1111 _
b1111 Y
b1111 \
14
02
b1 1
b1 B
b1 R
b1 a
b10 0
b10 A
b10 Q
b10 ^
b100 /
b100 @
b100 P
b100 [
b1000 .
b1000 ?
b1000 O
b1000 X
b1 -
b1 >
b1 N
b1 `
b10 ,
b10 =
b10 M
b10 ]
b100 +
b100 <
b100 L
b100 Z
b1000 *
b1000 ;
b1000 K
b1000 W
#340
b10 8
b10 E
#360
b1 "
b1 J
0!
0U
0V
b1011 \
b101 Y
15
04
b101 1
b101 B
b101 R
b101 a
b100 0
b100 A
b100 Q
b100 ^
b111 /
b111 @
b111 P
b111 [
b101 -
b101 >
b101 N
b101 `
b100 ,
b100 =
b100 M
b100 ]
b11 +
b11 <
b11 L
b11 Z
b10 *
b10 ;
b10 K
b10 W
#410
b1110 Y
b0 \
05
14
b111 1
b111 B
b111 R
b111 a
b1000 0
b1000 A
b1000 Q
b1000 ^
b110 /
b110 @
b110 P
b110 [
b11 .
b11 ?
b11 O
b11 X
b111 -
b111 >
b111 N
b111 `
b1000 ,
b1000 =
b1000 M
b1000 ]
b1001 +
b1001 <
b1001 L
b1001 Z
#460
b1 $
b1 H
1!
1U
1V
b1111 \
b1111 Y
04
13
b10 1
b10 B
b10 R
b10 a
b10 0
b10 A
b10 Q
b10 ^
b1 /
b1 @
b1 P
b1 [
b1 .
b1 ?
b1 O
b1 X
b10 -
b10 >
b10 N
b10 `
b10 ,
b10 =
b10 M
b10 ]
b1 +
b1 <
b1 L
b1 Z
b1 *
b1 ;
b1 K
b1 W
#480
b1 7
b1 D
#510
b10 %
b10 G
03
12
b111 1
b111 B
b111 R
b111 a
b1000 0
b1000 A
b1000 Q
b1000 ^
b1001 /
b1001 @
b1001 P
b1001 [
b10 .
b10 ?
b10 O
b10 X
b111 -
b111 >
b111 N
b111 `
b1000 ,
b1000 =
b1000 M
b1000 ]
b1001 +
b1001 <
b1001 L
b1001 Z
b10 *
b10 ;
b10 K
b10 W
#520
b10 6
b10 C
#560
b10 #
b10 I
0!
0S
0T
0U
b1110 b
b1001 _
b1001 \
14
02
b0 1
b0 B
b0 R
b0 a
b100 0
b100 A
b100 Q
b100 ^
b10 /
b10 @
b10 P
b10 [
b1000 .
b1000 ?
b1000 O
b1000 X
b1 -
b1 >
b1 N
b1 `
b10 ,
b10 =
b10 M
b10 ]
b100 +
b100 <
b100 L
b100 Z
b1000 *
b1000 ;
b1000 K
b1000 W
#610
b10 "
b10 J
1!
1S
1T
1U
b1111 b
b1111 _
b1111 \
15
04
b101 1
b101 B
b101 R
b101 a
b11 /
b11 @
b11 P
b11 [
b10 .
b10 ?
b10 O
b10 X
b101 -
b101 >
b101 N
b101 `
b100 ,
b100 =
b100 M
b100 ]
b11 +
b11 <
b11 L
b11 Z
b10 *
b10 ;
b10 K
b10 W
#650
b10 9
b10 F
#660
b11 #
b11 I
05
14
b111 1
b111 B
b111 R
b111 a
b1000 0
b1000 A
b1000 Q
b1000 ^
b1001 /
b1001 @
b1001 P
b1001 [
b111 -
b111 >
b111 N
b111 `
b1000 ,
b1000 =
b1000 M
b1000 ]
b1001 +
b1001 <
b1001 L
b1001 Z
#690
b11 8
b11 E
#710
b1 $
b1 H
0!
0V
0T
0U
b110 _
b100 \
b1110 Y
04
13
b1 ,
b1 =
b1 M
b1 ]
b10 +
b10 <
b10 L
b10 Z
b11 *
b11 ;
b11 K
b11 W
#760
b1110 _
b11 \
03
12
b1001 0
b1001 A
b1001 Q
b1001 ^
b101 /
b101 @
b101 P
b101 [
b11 .
b11 ?
b11 O
b11 X
b1000 ,
b1000 =
b1000 M
b1000 ]
b1001 +
b1001 <
b1001 L
b1001 Z
b10 *
b10 ;
b10 K
b10 W
#810
b100 #
b100 I
1!
1T
1V
1U
b1111 _
b1111 Y
b1111 \
14
02
b1 1
b1 B
b1 R
b1 a
b10 0
b10 A
b10 Q
b10 ^
b100 /
b100 @
b100 P
b100 [
b1000 .
b1000 ?
b1000 O
b1000 X
b1 -
b1 >
b1 N
b1 `
b10 ,
b10 =
b10 M
b10 ]
b100 +
b100 <
b100 L
b100 Z
b1000 *
b1000 ;
b1000 K
b1000 W
#840
b100 8
b100 E
#860
b10 "
b10 J
0!
0U
0V
b1011 \
b101 Y
15
04
b101 1
b101 B
b101 R
b101 a
b100 0
b100 A
b100 Q
b100 ^
b111 /
b111 @
b111 P
b111 [
b101 -
b101 >
b101 N
b101 `
b100 ,
b100 =
b100 M
b100 ]
b11 +
b11 <
b11 L
b11 Z
b10 *
b10 ;
b10 K
b10 W
#910
b1110 Y
b0 \
05
14
b111 1
b111 B
b111 R
b111 a
b1000 0
b1000 A
b1000 Q
b1000 ^
b110 /
b110 @
b110 P
b110 [
b11 .
b11 ?
b11 O
b11 X
b111 -
b111 >
b111 N
b111 `
b1000 ,
b1000 =
b1000 M
b1000 ]
b1001 +
b1001 <
b1001 L
b1001 Z
#960
b10 $
b10 H
1!
1U
1V
b1111 \
b1111 Y
04
13
b10 1
b10 B
b10 R
b10 a
b10 0
b10 A
b10 Q
b10 ^
b1 /
b1 @
b1 P
b1 [
b1 .
b1 ?
b1 O
b1 X
b10 -
b10 >
b10 N
b10 `
b10 ,
b10 =
b10 M
b10 ]
b1 +
b1 <
b1 L
b1 Z
b1 *
b1 ;
b1 K
b1 W
#980
b10 7
b10 D
#2000
1'
1:
